README
setup.py
sphinxcontrib/__init__.py
sphinxcontrib/proceduralimage.py
sphinxcontrib_proceduralimage.egg-info/PKG-INFO
sphinxcontrib_proceduralimage.egg-info/SOURCES.txt
sphinxcontrib_proceduralimage.egg-info/dependency_links.txt
sphinxcontrib_proceduralimage.egg-info/namespace_packages.txt
sphinxcontrib_proceduralimage.egg-info/not-zip-safe
sphinxcontrib_proceduralimage.egg-info/requires.txt
sphinxcontrib_proceduralimage.egg-info/top_level.txt