Metadata-Version: 1.0
Name: sphinxcontrib-proceduralimage
Version: 0.2
Summary: proceduralimage Sphinx extension
Home-page: https://github.com/timo/sphinxcontrib-proceduralimage
Author: Timo Paulssen
Author-email: timonator@perpetuum-immobile.de
License: BSD
Platform: any
Classifier: Development Status :: 3 - Alpha
Classifier: Intended Audience :: Developers
Classifier: Operating System :: OS Independent
Classifier: Programming Language :: Python
Classifier: License :: OSI Approved :: BSD License
Classifier: Topic :: Documentation
Classifier: Topic :: Software Development :: Documentation
Classifier: Topic :: Utilities
